llama_index/storage/kvstore/mongodb/__init__.py
llama_index/storage/kvstore/mongodb/base.py
llama_index_storage_kvstore_mongodb-0.5.0.dist-info/METADATA
llama_index_storage_kvstore_mongodb-0.5.0.dist-info/WHEEL
llama_index_storage_kvstore_mongodb-0.5.0.dist-info/licenses/LICENSE
llama_index_storage_kvstore_mongodb-0.5.0.dist-info/RECORD
